odoo/addons/agreement_repair/README.rst
odoo/addons/agreement_repair/__init__.py
odoo/addons/agreement_repair/__manifest__.py
odoo/addons/agreement_repair/i18n/agreement_repair.pot
odoo/addons/agreement_repair/i18n/de.po
odoo/addons/agreement_repair/models/__init__.py
odoo/addons/agreement_repair/models/agreement.py
odoo/addons/agreement_repair/models/repair.py
odoo/addons/agreement_repair/readme/CONTRIBUTORS.rst
odoo/addons/agreement_repair/readme/CREDITS.rst
odoo/addons/agreement_repair/readme/DESCRIPTION.rst
odoo/addons/agreement_repair/readme/ROADMAP.rst
odoo/addons/agreement_repair/readme/USAGE.rst
odoo/addons/agreement_repair/static/description/icon.png
odoo/addons/agreement_repair/static/description/index.html
odoo/addons/agreement_repair/views/agreement_view.xml
odoo/addons/agreement_repair/views/repair_view.xml
odoo11_addon_agreement_repair-11.0.0.0.1.99.dev10.dist-info/METADATA
odoo11_addon_agreement_repair-11.0.0.0.1.99.dev10.dist-info/WHEEL
odoo11_addon_agreement_repair-11.0.0.0.1.99.dev10.dist-info/top_level.txt
odoo11_addon_agreement_repair-11.0.0.0.1.99.dev10.dist-info/RECORD
